LICENSE
MANIFEST.in
README.rst
setup.cfg
setup.py
gapic_google_monitoring_v3.egg-info/PKG-INFO
gapic_google_monitoring_v3.egg-info/SOURCES.txt
gapic_google_monitoring_v3.egg-info/dependency_links.txt
gapic_google_monitoring_v3.egg-info/namespace_packages.txt
gapic_google_monitoring_v3.egg-info/requires.txt
gapic_google_monitoring_v3.egg-info/top_level.txt
google/__init__.py
google/__init__.pyc
google/cloud/__init__.py
google/cloud/__init__.pyc
google/cloud/gapic/__init__.py
google/cloud/gapic/monitoring/__init__.py
google/cloud/gapic/monitoring/v3/__init__.py
google/cloud/gapic/monitoring/v3/enums.py
google/cloud/gapic/monitoring/v3/group_service_api.py
google/cloud/gapic/monitoring/v3/group_service_client_config.json
google/cloud/gapic/monitoring/v3/metric_service_api.py
google/cloud/gapic/monitoring/v3/metric_service_client_config.json